purecpp_embed/RagPUREAI_embed.cpython-311-x86_64-linux-gnu.so
purecpp_embed/__init__.py
purecpp_embed-1.0.4.dist-info/METADATA
purecpp_embed-1.0.4.dist-info/WHEEL
purecpp_embed-1.0.4.dist-info/top_level.txt
purecpp_embed-1.0.4.dist-info/RECORD
